bambootools/__init__.py
bambootools/bambootools.py
BambooTools-0.4.0.dist-info/LICENSE.txt
BambooTools-0.4.0.dist-info/METADATA
BambooTools-0.4.0.dist-info/WHEEL
BambooTools-0.4.0.dist-info/top_level.txt
BambooTools-0.4.0.dist-info/RECORD
