Metadata-Version: 2.1
Name: BambooTools
Version: 0.4.0
Summary: Pandas extension to enchance your data analysis.
Home-page: https://github.com/KwstasMCPU/BambooTools
Author: Konstantinos Maravegias
Author-email: kwstas.maras@gmail.com
License: MIT
Project-URL: Documentation, https://github.com/KwstasMCPU/BambooTools
Project-URL: Changelog, https://github.com/KwstasMCPU/BambooTools/releases
Project-URL: Source, https://github.com/KwstasMCPU/BambooTools
Keywords: BambooTools,pandas,pandas extensions,data analysis,data science,analytics
Classifier: Development Status :: 4 - Beta
Classifier: Programming Language :: Python :: 3
Classifier: Intended Audience :: Developers
Classifier: Intended Audience :: Science/Research
Classifier: License :: OSI Approved :: MIT License
Requires-Python: >=3.8
License-File: LICENSE.txt
Requires-Dist: pandas >=1.5.3
Provides-Extra: dev
Requires-Dist: pytest >=7.4.2 ; extra == 'dev'
Requires-Dist: twine ; extra == 'dev'
Requires-Dist: seaborn ; extra == 'dev'
Requires-Dist: build ; extra == 'dev'
Requires-Dist: pre-commit ==3.5.0 ; extra == 'dev'
